scikit_plot-0.3.6.dist-info/METADATA
scikit_plot-0.3.6.dist-info/RECORD
scikit_plot-0.3.6.dist-info/WHEEL
scikit_plot-0.3.6.dist-info/top_level.txt
scikitplot/__init__.py
scikitplot/classifiers.py
scikitplot/cluster.py
scikitplot/clustering.py
scikitplot/decomposition.py
scikitplot/estimators.py
scikitplot/helpers.py
scikitplot/metrics.py
scikitplot/plotters.py
