Metadata-Version: 2.1
Name: scikit-plot
Version: 0.3.6
Summary: An intuitive library to add plotting functionality to scikit-learn objects.
Home-page: https://github.com/reiinakano/scikit-plot
Author: Reiichiro Nakano
Author-email: reiichiro.s.nakano@gmail.com
License: MIT License
Platform: any
Classifier: Programming Language :: Python
Classifier: Programming Language :: Python :: 2
Classifier: Programming Language :: Python :: 2.7
Classifier: Programming Language :: Python :: 3
Classifier: Programming Language :: Python :: 3.5
Classifier: Programming Language :: Python :: 3.6
Classifier: Natural Language :: English
Classifier: Intended Audience :: Developers
Classifier: Intended Audience :: Science/Research
Classifier: License :: OSI Approved :: MIT License
Classifier: Operating System :: OS Independent
Classifier: Topic :: Scientific/Engineering :: Visualization
Provides-Extra: testing
Requires-Dist: matplotlib (>=1.4.0)
Requires-Dist: scikit-learn (>=0.18)
Requires-Dist: scipy (>=0.9)
Requires-Dist: joblib (>=0.10)
Provides-Extra: testing
Requires-Dist: pytest; extra == 'testing'
